Metadata-Version: 2.1
Name: mdmcleaner
Version: 0.8.7
Summary: A pipeline for the assessment, classification and refinement of microbial dark matter SAGs and MAGs
Home-page: https://github.com/KIT-IBG-5/mdmcleaner
Author: John Vollmers
Author-email: john.vollmers@kit.edu
License: GPL-3.0
Classifier: Programming Language :: Python :: 3
License-File: LICENSE
Requires-Dist: biopython
Requires-Dist: numpy
